[
  {
    "title": "心形嵌花针织开衫",
    "url": "https://cdn-images.farfetch-contents.com/12/32/66/48/12326648_10965170_1000.jpg",
    "urlList": [
      "https://cdn-images.farfetch-contents.com/12/32/66/48/12326648_10965172_1000.jpg",
      "https://cdn-images.farfetch-contents.com/12/32/66/48/12326648_10965175_1000.jpg",
      "https://cdn-images.farfetch-contents.com/12/32/66/48/12326648_10965170_1000.jpg"
    ],
    "id": "68",
    "price": "2690",
    "description": "因商品数据较多,商品描述暂为同一个!   Hellessy 黑色 全棉 露肩套头衫。 深v领, 长袖, 罗纹底边及袖口, 粗针织设计, 平直下摆。"
  },
  {
    "title": "荷叶丝绒小礼服",
    "url": "https://cdn-images.farfetch-contents.com/12/47/12/62/12471262_11699184_1000.jpg",
    "urlList": [
      "https://cdn-images.farfetch-contents.com/12/47/12/62/12471262_11699192_1000.jpg",
      "https://cdn-images.farfetch-contents.com/12/47/12/62/12471262_11699197_1000.jpg",
      "https://cdn-images.farfetch-contents.com/12/47/12/62/12471262_11699184_1000.jpg"
    ],
    "id": "69",
    "price": "766",
    "description": "因商品数据较多,商品描述暂为同一个!   Hellessy 黑色 全棉 露肩套头衫。 深v领, 长袖, 罗纹底边及袖口, 粗针织设计, 平直下摆。"
  },
  {
    "title": "条纹针织连衣裙",
    "url": "https://cdn-images.farfetch-contents.com/12/46/05/45/12460545_11558428_1000.jpg",
    "urlList": [
      "https://cdn-images.farfetch-contents.com/12/46/05/45/12460545_11558435_1000.jpg",
      "https://cdn-images.farfetch-contents.com/12/46/05/45/12460545_11558446_1000.jpg",
      "https://cdn-images.farfetch-contents.com/12/46/05/45/12460545_11558428_1000.jpg"
    ],
    "id": "70",
    "price": "1545",
    "description": "因商品数据较多,商品描述暂为同一个!   Hellessy 黑色 全棉 露肩套头衫。 深v领, 长袖, 罗纹底边及袖口, 粗针织设计, 平直下摆。"
  },
  {
    "title": "花卉印花连衣裙",
    "url": "https://cdn-images.farfetch-contents.com/12/42/38/93/12423893_11366204_1000.jpg",
    "urlList": [
      "https://cdn-images.farfetch-contents.com/12/42/38/93/12423893_11366215_1000.jpg",
      "https://cdn-images.farfetch-contents.com/12/42/38/93/12423893_11366226_1000.jpg",
      "https://cdn-images.farfetch-contents.com/12/42/38/93/12423893_11366204_1000.jpg"
    ],
    "id": "71",
    "price": "2690",
    "description": "因商品数据较多,商品描述暂为同一个!   Hellessy 黑色 全棉 露肩套头衫。 深v领, 长袖, 罗纹底边及袖口, 粗针织设计, 平直下摆。"
  },
  {
    "title": "",
    "url": "https://cdn-images.farfetch-contents.com/12/32/66/48/12326648_10965170_1000.jpg",
    "urlList": [
      "https://cdn-images.farfetch-contents.com/12/32/66/48/12326648_10965172_1000.jpg",
      "https://cdn-images.farfetch-contents.com/12/32/66/48/12326648_10965175_1000.jpg",
      "https://cdn-images.farfetch-contents.com/12/32/66/48/12326648_10965170_1000.jpg"
    ],
    "id": "72",
    "price": "3024",
    "description": "因商品数据较多,商品描述暂为同一个!   Hellessy 黑色 全棉 露肩套头衫。 深v领, 长袖, 罗纹底边及袖口, 粗针织设计, 平直下摆。"
  },
  {
    "title": "Rainbow伞状连衣裙",
    "url": "https://cdn-images.farfetch-contents.com/12/38/43/58/12384358_11320830_1000.jpg",
    "urlList": [
      "https://cdn-images.farfetch-contents.com/12/38/43/58/12384358_11320831_1000.jpg",
      "https://cdn-images.farfetch-contents.com/12/38/43/58/12384358_11320833_1000.jpg",
      "https://cdn-images.farfetch-contents.com/12/38/43/58/12384358_11320830_1000.jpg"
    ],
    "id": "73",
    "price": "955",
    "description": "因商品数据较多,商品描述暂为同一个!   Hellessy 黑色 全棉 露肩套头衫。 深v领, 长袖, 罗纹底边及袖口, 粗针织设计, 平直下摆。"
  }
]